sera/__init__.py
sera/constants.py
sera/exports/__init__.py
sera/exports/schema.py
sera/exports/test.py
sera/libs/__init__.py
sera/libs/api_helper.py
sera/libs/api_test_helper.py
sera/libs/base_orm.py
sera/libs/base_search.py
sera/libs/base_service.py
sera/libs/digraph/__init__.py
sera/libs/digraph/_context.py
sera/libs/digraph/_edge.py
sera/libs/digraph/_execution_summary.py
sera/libs/digraph/_graph.py
sera/libs/digraph/_node.py
sera/libs/digraph/_node_input.py
sera/libs/digraph/_node_output.py
sera/libs/digraph/_types.py
sera/libs/middlewares/__init__.py
sera/libs/middlewares/auth.py
sera/libs/middlewares/uscp.py
sera/libs/search_helper.py
sera/make/__init__.py
sera/make/__main__.py
sera/make/make_app.py
sera/make/make_python_services.py
sera/make/make_typescript_model.py
sera/make/py_backend/__init__.py
sera/make/py_backend/api/__init__.py
sera/make/py_backend/api/make_api.py
sera/make/py_backend/api/make_create_api.py
sera/make/py_backend/api/make_get_by_id_api.py
sera/make/py_backend/api/make_has_api.py
sera/make/py_backend/api/make_search_api.py
sera/make/py_backend/api/make_update_api.py
sera/make/py_backend/logic/__init__.py
sera/make/py_backend/logic/make_create_logic.py
sera/make/py_backend/logic/make_logic.py
sera/make/py_backend/logic/make_logic_graph.py
sera/make/py_backend/logic/make_search_logic.py
sera/make/py_backend/logic/make_update_logic.py
sera/make/py_backend/misc.py
sera/make/py_backend/models/__init__.py
sera/make/py_backend/models/make_data_model.py
sera/make/py_backend/models/make_enums.py
sera/make/py_backend/models/make_relational_model.py
sera/make/py_backend/system_controlled_property.py
sera/make/ts_frontend/__init__.py
sera/make/ts_frontend/make_class_schema.py
sera/make/ts_frontend/make_draft_model.py
sera/make/ts_frontend/make_enums.py
sera/make/ts_frontend/make_query.py
sera/make/ts_frontend/misc.py
sera/misc/__init__.py
sera/misc/_cache_cleaner.py
sera/misc/_file_writer.py
sera/misc/_formatter.py
sera/misc/_utils.py
sera_2-1.33.3.dist-info/METADATA
sera_2-1.33.3.dist-info/WHEEL
sera_2-1.33.3.dist-info/RECORD
