Metadata-Version: 2.4
Name: sera-2
Version: 1.33.3
Summary: 
Author: Binh Vu
Author-email: bvu687@gmail.com
Requires-Python: >=3.12,<4.0
Classifier: Programming Language :: Python :: 3
Classifier: Programming Language :: Python :: 3.12
Classifier: Programming Language :: Python :: 3.13
Classifier: Programming Language :: Python :: 3.14
Requires-Dist: black (==25.1.0)
Requires-Dist: codegen-2 (>=2.15.6,<3.0.0)
Requires-Dist: graph-wrapper (>=1.7.3,<2.0.0)
Requires-Dist: isort (==6.0.1)
Requires-Dist: litestar (>=2.15.1,<3.0.0)
Requires-Dist: loguru (>=0.7.0,<0.8.0)
Requires-Dist: msgspec (>=0.19.0,<0.20.0)
Requires-Dist: serde2 (>=1.9.2,<2.0.0)
Requires-Dist: sqlalchemy[asyncio] (>=2.0.41,<3.0.0)
Requires-Dist: tqdm (>=4.67.1,<5.0.0)
Requires-Dist: typer (>=0.16.0,<0.17.0)
Project-URL: Repository, https://github.com/binh-vu/sera
